fairchem/__init__.py
fairchem_data-0.0.0b0.dist-info/METADATA
fairchem_data-0.0.0b0.dist-info/WHEEL
fairchem_data-0.0.0b0.dist-info/top_level.txt
fairchem_data-0.0.0b0.dist-info/RECORD
