Metadata-Version: 2.1
Name: fairchem-data
Version: 0.0.0b0
Summary: Coming soon
Author-email: Misko Dzamba <misko@meta.com>, Muhammed Shuaibi <mshuaibi@meta.com>, Luis Barroso-Luque <lbluque@meta.com>
